threadsafe_shell.py
threadsafe_shell-1.5.1.dist-info/LICENSE
threadsafe_shell-1.5.1.dist-info/METADATA
threadsafe_shell-1.5.1.dist-info/WHEEL
threadsafe_shell-1.5.1.dist-info/top_level.txt
threadsafe_shell-1.5.1.dist-info/RECORD
